{"version":1,"resource":"file:///mnt/SDA2/Code%20Pages/dawn/userconfig.js","entries":[{"id":"eTQI.js","timestamp":1720874870109},{"id":"nJIk.js","timestamp":1720874914823},{"id":"JJTz.js","timestamp":1720874950024},{"id":"JjhG.js","timestamp":1720874982066},{"id":"9a6U.js","timestamp":1720875005921},{"id":"kA1J.js","timestamp":1720875323540},{"id":"dCtu.js","timestamp":1720875340465},{"id":"blpd.js","timestamp":1720875353888},{"id":"lLoZ.js","timestamp":1720875374911},{"id":"xXX1.js","timestamp":1720875389733},{"id":"iCql.js","timestamp":1720875412593},{"id":"SU1g.js","timestamp":1720875441399},{"id":"ngGO.js","timestamp":1720875459720},{"id":"YnFw.js","timestamp":1720875498569},{"id":"QE8j.js","timestamp":1720875514828},{"id":"m55A.js","timestamp":1720875601015},{"id":"erU5.js","timestamp":1720875620066},{"id":"35nF.js","timestamp":1720875651334},{"id":"Bxua.js","timestamp":1720875673929},{"id":"7JKP.js","timestamp":1720875705600},{"id":"fP6m.js","timestamp":1720875762580},{"id":"pXhb.js","timestamp":1720875912589},{"id":"ytG9.js","timestamp":1720875928774},{"id":"6fyN.js","timestamp":1720875959175},{"id":"RhQJ.js","timestamp":1720876011705},{"id":"2oPv.js","timestamp":1720876031307},{"id":"7I8W.js","timestamp":1720876055339},{"id":"kwQt.js","timestamp":1720876099239},{"id":"hOMk.js","timestamp":1720876120393},{"id":"xLj2.js","timestamp":1720942192551},{"id":"QaVH.js","timestamp":1720942238842},{"id":"39wj.js","timestamp":1720942265300},{"id":"lL3O.js","timestamp":1720942308657},{"id":"Znaw.js","timestamp":1720942336374},{"id":"9aMQ.js","timestamp":1720942348051},{"id":"HgsJ.js","timestamp":1720942399319},{"id":"rzCx.js","timestamp":1720942419927},{"id":"8kFL.js","timestamp":1720942460624},{"id":"YqLA.js","timestamp":1720942484238},{"id":"rpjk.js","timestamp":1720942512253},{"id":"4fMz.js","timestamp":1720942522496},{"id":"UeJL.js","timestamp":1720942605868},{"id":"Kkn3.js","timestamp":1720942622053},{"id":"biN8.js","timestamp":1720942647176},{"id":"uqRP.js","timestamp":1720942660787},{"id":"yfEC.js","timestamp":1720942672864},{"id":"2355.js","timestamp":1720942715738},{"id":"LHzX.js","timestamp":1720953405037},{"id":"WtqL.js","timestamp":1720953440721},{"id":"iSxy.js","timestamp":1720953467360}]}